{
  "captured_at": "2026-06-27T01:51:47.179610+00:00",
  "platform": {
    "machine": "arm64",
    "platform": "macOS-26.5.1-arm64-arm-64bit-Mach-O",
    "python": "3.14.5 (main, May 10 2026, 10:21:34) [Clang 21.0.0 (clang-2100.0.123.102)]",
    "python_executable": "/opt/homebrew/opt/python@3.14/bin/python3.14",
    "release": "25.5.0",
    "system": "Darwin"
  },
  "repository": {
    "branch": {
      "available": true,
      "command": [
        "git",
        "branch",
        "--show-current"
      ],
      "returncode": 0,
      "stderr": "",
      "stdout": "main"
    },
    "docker_path": "/opt/homebrew/bin/docker",
    "head": {
      "available": true,
      "command": [
        "git",
        "rev-parse",
        "HEAD"
      ],
      "returncode": 0,
      "stderr": "",
      "stdout": "b5a8a703506b14bb954fcc5ce1ad32c518763cc7"
    },
    "latest_commits": {
      "available": true,
      "command": [
        "git",
        "log",
        "--oneline",
        "--decorate",
        "--max-count=8"
      ],
      "returncode": 0,
      "stderr": "",
      "stdout": "b5a8a70 (HEAD -> main, origin/main, origin/HEAD) Add W10 reproducibility package\n88f23ec Add W8 midpoint evidence package\n5a47cea Add W6 early validation package\n674fa58 Add W6 validation harness\ne501323 Add W5 evidence addendum\n3475ccf (tag: w5-baseline) Add W5 implementation sprint baseline\nb5b2702 Add W4 design review package\na9d9e76 Record W2 proposal feedback"
    },
    "runsc_path": null,
    "status": {
      "available": true,
      "command": [
        "git",
        "status",
        "--short",
        "--branch"
      ],
      "returncode": 0,
      "stderr": "",
      "stdout": "## main...origin/main\n M Makefile\n M README.md\n M docs/ai-use-log.md\n M engineering-log.md\n?? docs/06-hard-stop-3/evidence-target-rerun.zip\n?? docs/06-hard-stop-3/evidence-target.zip\n?? docs/06-hard-stop-3/evidence.zip\n?? docs/12-hard-stop-6/\n?? scripts/run_final_evidence.py"
    }
  },
  "tools": {
    "docker_client": {
      "available": true,
      "command": [
        "docker",
        "version"
      ],
      "returncode": 0,
      "stderr": "",
      "stdout": "Client: Docker Engine - Community\n Version:           27.5.1\n API version:       1.47\n Go version:        go1.23.5\n Git commit:        9f9e405801\n Built:             Tue Jan 21 23:46:20 2025\n OS/Arch:           darwin/arm64\n Context:           colima\n\nServer: Docker Engine - Community\n Engine:\n  Version:          27.4.0\n  API version:      1.47 (minimum version 1.24)\n  Go version:       go1.22.10\n  Git commit:       92a8393\n  Built:            Sat Dec  7 10:39:01 2024\n  OS/Arch:          linux/arm64\n  Experimental:     false\n containerd:\n  Version:          1.7.24\n  GitCommit:        88bf19b2105c8b17560993bee28a01ddc2f97182\n runc:\n  Version:          1.2.2\n  GitCommit:        v1.2.2-0-g7cb3632\n docker-init:\n  Version:          0.19.0\n  GitCommit:        de40ad0"
    },
    "docker_info": {
      "available": true,
      "command": [
        "docker",
        "info"
      ],
      "returncode": 0,
      "stderr": "WARNING: Plugin \"/Users/ericliang/.docker/cli-plugins/docker-buildx\" is not valid: failed to fetch metadata: fork/exec /Users/ericliang/.docker/cli-plugins/docker-buildx: no such file or directory\nWARNING: Plugin \"/Users/ericliang/.docker/cli-plugins/docker-compose\" is not valid: failed to fetch metadata: fork/exec /Users/ericliang/.docker/cli-plugins/docker-compose: no such file or directory\nWARNING: bridge-nf-call-iptables is disabled\nWARNING: bridge-nf-call-ip6tables is disabled",
      "stdout": "Client: Docker Engine - Community\n Version:    27.5.1\n Context:    colima\n Debug Mode: false\n Plugins:\n\nServer:\n Containers: 0\n  Running: 0\n  Paused: 0\n  Stopped: 0\n Images: 0\n Server Version: 27.4.0\n Storage Driver: overlay2\n  Backing Filesystem: extfs\n  Supports d_type: true\n  Using metacopy: false\n  Native Overlay Diff: true\n  userxattr: false\n Logging Driver: json-file\n Cgroup Driver: cgroupfs\n Cgroup Version: 2\n Plugins:\n  Volume: local\n  Network: bridge host ipvlan macvlan null overlay\n  Log: awslogs fluentd gcplogs gelf journald json-file local splunk syslog\n Swarm: inactive\n Runtimes: io.containerd.runc.v2 runc\n Default Runtime: runc\n Init Binary: docker-init\n containerd version: 88bf19b2105c8b17560993bee28a01ddc2f97182\n runc version: v1.2.2-0-g7cb3632\n init version: de40ad0\n Security Options:\n  apparmor\n  seccomp\n   Profile: builtin\n  cgroupns\n Kernel Version: 6.8.0-50-generic\n Operating System: Ubuntu 24.04.1 LTS\n OSType: linux\n Architecture: aarch64\n CPUs: 2\n Total Memory: 1.913GiB\n Name: colima\n ID: 250c0738-3a14-43d0-882a-d464c137ef03\n Docker Root Dir: /var/lib/docker\n Debug Mode: false\n Experimental: false\n Insecure Registries:\n  127.0.0.0/8\n Live Restore Enabled: false"
    },
    "git": {
      "available": true,
      "command": [
        "git",
        "--version"
      ],
      "returncode": 0,
      "stderr": "",
      "stdout": "git version 2.53.0"
    },
    "make": {
      "available": true,
      "command": [
        "make",
        "--version"
      ],
      "returncode": 0,
      "stderr": "",
      "stdout": "GNU Make 3.81\nCopyright (C) 2006  Free Software Foundation, Inc.\nThis is free software; see the source for copying conditions.\nThere is NO warranty; not even for MERCHANTABILITY or FITNESS FOR A\nPARTICULAR PURPOSE.\n\nThis program built for i386-apple-darwin11.3.0"
    },
    "runsc": {
      "available": false,
      "command": [
        "runsc",
        "--version"
      ],
      "returncode": null,
      "stderr": "[Errno 2] No such file or directory: 'runsc'",
      "stdout": ""
    }
  }
}
